AUTHORS
LICENSE
MANIFEST.in
README.rst
flask_celery.py
setup.cfg
setup.py
Flask_Celery.egg-info/PKG-INFO
Flask_Celery.egg-info/SOURCES.txt
Flask_Celery.egg-info/dependency_links.txt
Flask_Celery.egg-info/not-zip-safe
Flask_Celery.egg-info/requires.txt
Flask_Celery.egg-info/top_level.txt
example/manage.py
example/myapp.py
requirements/default.txt
requirements/test.txt
tests/__init__.py
tests/test_basic.py